pymarszpace/__init__.py
pymarszpace/marszpace.py
pymarszpace-1.0.1.dist-info/LICENSE
pymarszpace-1.0.1.dist-info/METADATA
pymarszpace-1.0.1.dist-info/WHEEL
pymarszpace-1.0.1.dist-info/top_level.txt
pymarszpace-1.0.1.dist-info/RECORD
