Metadata-Version: 2.1
Name: pymarszpace
Version: 1.0.1
Summary: Just a Marszpace package, nothing much.
Home-page: https://bitbucket.org/CCSleep/pymarszpace/
Author: CCSleep
Author-email: admin@ccsleep.net
License: UNKNOWN
Platform: UNKNOWN
Classifier: Programming Language :: Python :: 3
Classifier: License :: OSI Approved :: MIT License
Classifier: Operating System :: OS Independent
Requires-Python: >=3.6
